Neuromorphic_Computing/hopfiled_network_v1/Final/defines.v

`define NEURON_COUNT 4'd8       // number of neurons
`define NEURON_INDEX_MAX 4'd7
`define STATE_INPUT 2'd0
`define STATE_UPDATING 2'd1
`define STATE_LEARNING 2'd2

`define PATTERN_INPUT_1 8'b11100000
`define PATTERN_INPUT_2 8'b00001110
`define PATTERN_INPUT_3 8'b10100000
`define PATTERN_INPUT_4 8'b00001100
`define THRESHOLD_UPPER 8'b10000000
`define THRESHOLD_LOWER 8'd1

Neuromorphic_Computing/hopfiled_network_v1/Final/HopfieldDatapath_v1.v
//==============================================================================
// Datapath for Simon Project
//==============================================================================

`include "defines.v"

module HopfieldDatapath(
	// External Inputs
	input clk, // Clock
	input rst, // RESET
	input  [`NEURON_INDEX_MAX:0] pattern_input,       // neuron input pattern

	

	//Datapath control signals
	input modify_neuron, // True if neuron state is to be modified
	input modify_neuron_using_input, // True if neuron state should be set to input, only happens if modify_neuron is True
	input modify_weights, // True if weights are to be modified
	
	// Datapath Outputs to Control
	output reg same_input, // True if the same input was present at the previous clock cycle
	output reg converged, // True if same neuron values occur at consecutive clock cycles for all neurons

	// External Outputs
	output reg [`NEURON_INDEX_MAX: 0] neuron_states // states of all neurons, should the [] go after the neuron_states

	// output reg [15: 0] weights_out // N regs where each reg has N - 1 entries


);

	// Declare Local Vars Here
	// weights and neurons
	reg [`NEURON_INDEX_MAX: 0][`NEURON_INDEX_MAX:0] weights; // N regs where each reg has N - 1 entries
	reg [`NEURON_INDEX_MAX: 0][`NEURON_INDEX_MAX:0] new_weights; // N regs where each reg has N - 1 entries
	
	reg [`NEURON_INDEX_MAX: 0] neuron_states_new; // new states of all neurons, should the [] go after the neuron_states
	reg [`NEURON_INDEX_MAX:0] pattern_input_prev;       // neuron input pattern previous timestep
	// updating
	reg [`NEURON_INDEX_MAX:0] products; // each activation multiplied by each weight
	reg [`NEURON_INDEX_MAX:0][`NEURON_INDEX_MAX:0] activation; // sum of products for a neuron

	reg [`NEURON_INDEX_MAX:0] vec;


	integer i;
	integer j;
	integer k;
	integer l;
	integer z;

	// 

	//----------------------------------------------------------------------
	// Internal Logic -- Manipulate Registers, ALU's, Memories Local to
	// the Datapath
	//----------------------------------------------------------------------
		
	
	always @(posedge clk) begin
		// Sequential Internal Logic Here
		pattern_input_prev <= pattern_input;
		activation <= 0;
		
		if (modify_weights) begin // learning
			weights <= new_weights;
			// for (z = 0; z < `NEURON_COUNT; z+=1) begin
			// 	weights[z] <= new_weights[z];
			// end
			
			// weights_out <= { << { weights}};
		end

		if (modify_neuron & ~modify_neuron_using_input) begin // updating
			neuron_states <= neuron_states_new;
		
		end

		else if (modify_neuron) begin // input
			neuron_states <= pattern_input;
		end
		if (rst) begin
		  weights <= 0;//16'b0101101001001000;
		  new_weights <= 0;
		  activation <= 0;
		end
		
	end

	

	//----------------------------------------------------------------------
	// Output Logic -- Set Datapath Outputs
	//----------------------------------------------------------------------

	always @( * ) begin
		// Output Logic Here
		same_input = (pattern_input == pattern_input_prev); // same input
		converged = (neuron_states == neuron_states_new); // True if no further updating occuring
		// Updating
		
		for (i = 0; i < `NEURON_COUNT; i+=1) begin
			products = neuron_states & weights[i];//~(neuron_states ^ weights[i]);
			// activation = 0;
			// sum the bits
			for (j = 0; j < `NEURON_COUNT; j +=1) begin
				if (i != j) begin
					activation[i] = activation[i] + products[j];
				end
			end
			//activation[i] = activation[i] - (`NEURON_COUNT - 1 - activation[i]); // do not include self neuron
			neuron_states_new[i] = (activation[i] >= `THRESHOLD_LOWER);// & activation[i] < `THRESHOLD_UPPER); // ReLu
		end
		// new weights, learning
		for (k=0; k < `NEURON_COUNT; k += 1) begin
			if (pattern_input[k] == 1) begin
				vec = 0 - 1;
			end
			else if (pattern_input[k] == 0) begin
				vec = 0;
			end
			//new_weights[k] = weights[k] | (~(pattern_input ^ vec));
			new_weights[k] = weights[k] | (pattern_input & vec);
			
		end

	end


	

endmodule

Neuromorphic_Computing/hopfiled_network_v1/Final/HopfieldDatapath.t.v
//===============================================================================
// Testbench Module for Simon
//===============================================================================
`timescale 1ns/100ps

`include "HopfieldDatapath_v1.v"
`include "defines.v"

`define ASSERT_EQ(ONE, TWO, MSG)               \
	begin                                      \
		if ((ONE) !== (TWO)) begin             \
			$display("\t[FAILURE]:%s", (MSG)); \
		end                                    \
	end #0

`define SET(VAR, VALUE) $display("Setting %s to %s...", "VAR", "VALUE"); #1; VAR = (VALUE); #1

`define CLOCK $display("Pressing uclk..."); #1; clk = 1; #1; clk = 0; #1

`define SHOW_MODE(MODE) $display("\nEntering Mode: %s\n-----------------------------------", MODE)

module HopfielddpathTest;

	// Local Vars
	reg clk; // Clock
    reg rst; // RESET
    reg [`NEURON_INDEX_MAX:0] pattern_input; // neuron input pattern
    reg modify_neuron; // True if neuron state is to be modified
	reg modify_neuron_using_input; // True if neuron state should be set to input, only happens if modify_neuron is True
	reg modify_weights; // True if weights are to be modified

    wire same_input; // True if the same input was present at the previous clock cycle
    wire converged; // True if same neuron values occur at consecutive clock cycles for all neurons
    wire [`NEURON_INDEX_MAX: 0] neuron_states; // states of all neurons, should the [] go after the neuron_states
    // wire [15:0] weights_out;


   



    	// VCD Dump
	initial begin
		$dumpfile("HopfieldDatapathTest.vcd");
        // for (idx = 0; idx < 64; idx = idx + 1) begin
		// 	$dumpvars(0, simon.dpath.mem.mem[idx]);
		// end
		$dumpvars;
	end

	// Controller Module
	HopfieldDatapath dpath(
		.clk(clk),
        .rst(rst),
        .pattern_input(pattern_input),
        .modify_neuron(modify_neuron),
        .modify_neuron_using_input(modify_neuron_using_input),
        .modify_weights(modify_weights),
        .same_input(same_input),
        .converged(converged),
        .neuron_states(neuron_states)

        //.state(state)
	);


	// Main Test Logic
	initial begin
		// Tick the clock
		`SHOW_MODE("Unknown");
        `SET(rst, 1);
		`CLOCK;
        `SET(rst, 0);
		`CLOCK;

        //-----------------------------------------------
		// New Input
		// ----------------------------------------------
        `SHOW_MODE("INPUT");
        `SET(modify_neuron, 1);
        `SET(modify_neuron_using_input, 1);
        `SET(pattern_input, `PATTERN_INPUT_1);

        `CLOCK;

		//-----------------------------------------------
		// CONFIRM INPUT
		// ----------------------------------------------
        `ASSERT_EQ(neuron_states, `PATTERN_INPUT_1, "The neuron statesd should be PATTERN_INPUT_1!");

        `CLOCK;




         //-----------------------------------------------
		// New Input
		// ----------------------------------------------
        `SHOW_MODE("INPUT");
        `SET(modify_neuron, 1);
        `SET(modify_neuron_using_input, 0);
        `CLOCK;

		// //-----------------------------------------------
		// // CONFIRM INPUT
		// // ----------------------------------------------
        // `ASSERT_EQ(neuron_states, `PATTERN_INPUT_1, "The neuron statesd should be PATTERN_INPUT_1!");

        `CLOCK;
        `CLOCK;
        `CLOCK;

        //-----------------------------------------------
		// LEARN
		// ----------------------------------------------
        `SHOW_MODE("MODIFY WEIGHTs");
        `SET(modify_weights, 1);
        `SET(modify_neuron, 0);
        `CLOCK;
        `CLOCK;
        `SET(modify_weights, 0);
        `SET(modify_neuron, 1);
        `CLOCK;
        `CLOCK;
         //-----------------------------------------------
		// New Input
		// ----------------------------------------------
        `SHOW_MODE("INPUT");
        `SET(modify_neuron, 1);
        `SET(modify_neuron_using_input, 1);
        `SET(pattern_input, `PATTERN_INPUT_2);
        `CLOCK
        `CLOCK
        `SET(modify_neuron, 1);
        `SET(modify_neuron_using_input, 0);
        `CLOCK;
        `CLOCK;
        `CLOCK

        //-----------------------------------------------
		// LEARN
		// ----------------------------------------------
        `SHOW_MODE("MODIFY WEIGHTs");
        `SET(modify_weights, 1);
        `SET(modify_neuron, 0);
        `CLOCK;
        `CLOCK;
        `SET(modify_weights, 0);
        `SET(modify_neuron, 1);
        `CLOCK;
        `CLOCK;
        //-----------------------------------------------
		// New Input
		// ----------------------------------------------
        `SHOW_MODE("INPUT");
        `SET(modify_neuron, 1);
        `SET(modify_neuron_using_input, 1);
        `SET(pattern_input, `PATTERN_INPUT_3);
        `CLOCK
        `CLOCK
        `SET(modify_neuron, 1);
        `SET(modify_neuron_using_input, 0);
        `CLOCK;
        `CLOCK;
        `CLOCK;
        `CLOCK;
        `CLOCK;
        `CLOCK;

        //-----------------------------------------------
		// New Input
		// ----------------------------------------------
        `SHOW_MODE("INPUT");
        `SET(modify_neuron, 1);
        `SET(modify_neuron_using_input, 1);
        `SET(pattern_input, `PATTERN_INPUT_4);
        `CLOCK
        `CLOCK
        `SET(modify_neuron, 1);
        `SET(modify_neuron_using_input, 0);
        `CLOCK;
        `CLOCK;
        `CLOCK;
        `CLOCK;
        `CLOCK;
        `CLOCK;



        


		$display("\nTESTS COMPLETED");
		$finish;
	end
endmodule

Neuromorphic_Computing/hopfiled_network_v1/Final/HopfieldDatapathTest.vcd
$date
	Mon Dec 27 20:23:35 2021
$end
$version
	Icarus Verilog
$end
$timescale
	100ps
$end
$scope module HopfielddpathTest $end
$var wire 1 ! same_input $end
$var wire 8 " neuron_states [7:0] $end
$var wire 1 # converged $end
$var reg 1 $ clk $end
$var reg 1 % modify_neuron $end
$var reg 1 & modify_neuron_using_input $end
$var reg 1 ' modify_weights $end
$var reg 8 ( pattern_input [7:0] $end
$var reg 1 ) rst $end
$scope module dpath $end
$var wire 1 $ clk $end
$var wire 1 % modify_neuron $end
$var wire 1 & modify_neuron_using_input $end
$var wire 1 ' modify_weights $end
$var wire 8 * pattern_input [7:0] $end
$var wire 1 ) rst $end
$var reg 64 + activation [63:0] $end
$var reg 1 # converged $end
$var reg 8 , neuron_states [7:0] $end
$var reg 8 - neuron_states_new [7:0] $end
$var reg 64 . new_weights [63:0] $end
$var reg 8 / pattern_input_prev [7:0] $end
$var reg 8 0 products [7:0] $end
$var reg 1 ! same_input $end
$var reg 8 1 vec [7:0] $end
$var reg 64 2 weights [63:0] $end
$var integer 32 3 i [31:0] $end
$var integer 32 4 j [31:0] $end
$var integer 32 5 k [31:0] $end
$upscope $end
$upscope $end
$enddefinitions $end
#0
$dumpvars
bx 5
bx 4
bx 3
bx 2
bx 1
bx 0
bx /
bx .
bx -
bx ,
bx +
bx *
x)
bx (
x'
x&
x%
x$
x#
bx "
x!
$end
#10
1)
#30
b1000 5
b0 -
b1000 4
b0 0
b1000 3
bx .
b0 2
b0 +
1$
#40
0$
#60
0)
#80
1$
#90
0$
#110
1%
#130
1&
#150
b1110000011100000111000000000000000000000000000000000000000000000 .
b11111111 1
b1000 5
b1000 4
b1000 3
b11100000 (
b11100000 *
#170
b11111111 1
b1000 5
b1000 4
b1000 3
0#
1!
b11100000 "
b11100000 ,
b11100000 /
1$
#180
0$
#200
1$
#210
0$
#250
0&
#270
b11111111 1
b1000 5
b1000 4
b1000 3
1#
b0 "
b0 ,
1$
#280
0$
#300
1$
#310
0$
#330
1$
#340
0$
#360
1$
#370
0$
#390
1'
#410
0%
#430
b11111111 1
b1000 5
b1000 4
b1000 3
b1110000011100000111000000000000000000000000000000000000000000000 2
1$
#440
0$
#460
1$
#470
0$
#490
0'
#510
1%
#530
1$
#540
0$
#560
1$
#570
0$
#610
1&
#630
b1110000011100000111000000000000000001110000011100000111000000000 .
b0 1
b1000 5
b1000 4
b1000 3
0!
b1110 (
b1110 *
#650
b0 1
b1000 5
b1000 4
b1000 3
0#
1!
b1110 "
b1110 ,
b1110 /
1$
#660
0$
#680
1$
#690
0$
#730
0&
#750
b0 1
b1000 5
b1000 4
b1000 3
1#
b0 "
b0 ,
1$
#760
0$
#780
1$
#790
0$
#810
1$
#820
0$
#840
1'
#860
0%
#880
b0 1
b1000 5
b1000 4
b1000 3
b1110000011100000111000000000000000001110000011100000111000000000 2
1$
#890
0$
#910
1$
#920
0$
#940
0'
#960
1%
#980
1$
#990
0$
#1010
1$
#1020
0$
#1060
1&
#1080
b11111111 1
b1000 5
b1000 4
b1000 3
0!
b10100000 (
b10100000 *
#1100
b11111111 1
b1000 5
b11100000 -
b100000010000000010000000000000000000000000000000000000000 +
b10100000 0
b1000 4
b1000 3
0#
1!
b10100000 "
b10100000 ,
b10100000 /
1$
#1110
0$
#1130
b11111111 1
b1000 5
b1000 4
b10100000 0
b1000 3
b100000010000000010000000000000000000000000000000000000000 +
1$
#1140
0$
#1180
0&
#1200
b11111111 1
b1000 5
b1000 4
b11100000 0
b1000 3
1#
b11100000 "
b11100000 ,
b1000000010000000100000000000000000000000000000000000000000 +
1$
#1210
0$
#1230
b11111111 1
b1000 5
b1000 4
b11100000 0
b1000 3
b1000000010000000100000000000000000000000000000000000000000 +
1$
#1240
0$
#1260
b11111111 1
b1000 5
b1000 4
b11100000 0
b1000 3
b1000000010000000100000000000000000000000000000000000000000 +
1$
#1270
0$
#1290
b11111111 1
b1000 5
b1000 4
b11100000 0
b1000 3
b1000000010000000100000000000000000000000000000000000000000 +
1$
#1300
0$
#1320
b11111111 1
b1000 5
b1000 4
b11100000 0
b1000 3
b1000000010000000100000000000000000000000000000000000000000 +
1$
#1330
0$
#1350
b11111111 1
b1000 5
b1000 4
b11100000 0
b1000 3
b1000000010000000100000000000000000000000000000000000000000 +
1$
#1360
0$
#1400
1&
#1420
b0 1
b1000 5
b10000000100000001000000000000000000000000000000000000000000 +
b1000 4
b11100000 0
b1000 3
0!
b1100 (
b1100 *
#1440
b0 1
b1000 5
b1110 -
b1000 4
b0 0
b1000 3
0#
1!
b1100 "
b1100 ,
b1000000010000001000000000 +
b1100 /
1$
#1450
0$
#1470
b0 1
b1000 5
b0 0
b1000 4
b1000 3
b1000000010000001000000000 +
1$
#1480
0$
#1520
0&
#1540
b0 1
b1000 5
b0 0
b1000 4
b1000 3
1#
b1110 "
b1110 ,
b10000000100000001000000000 +
1$
#1550
0$
#1570
b0 1
b1000 5
b0 0
b1000 4
b1000 3
b10000000100000001000000000 +
1$
#1580
0$
#1600
b0 1
b1000 5
b0 0
b1000 4
b1000 3
b10000000100000001000000000 +
1$
#1610
0$
#1630
b0 1
b1000 5
b0 0
b1000 4
b1000 3
b10000000100000001000000000 +
1$
#1640
0$
#1660
b0 1
b1000 5
b0 0
b1000 4
b1000 3
b10000000100000001000000000 +
1$
#1670
0$
#1690
b0 1
b1000 5
b0 0
b1000 4
b1000 3
b10000000100000001000000000 +
1$
